linuxnet/__init__.py
linuxnet/qos/__init__.py
linuxnet/qos/config.py
linuxnet/qos/deps.py
linuxnet/qos/exceptions.py
linuxnet/qos/extension.py
linuxnet/qos/handle.py
linuxnet/qos/metadata.py
linuxnet/qos/parsers.py
linuxnet/qos/tcunit.py
linuxnet/qos/util.py
linuxnet/qos/filters/__init__.py
linuxnet/qos/filters/filter.py
linuxnet/qos/filters/fwfilter.py
linuxnet/qos/filters/u32filter.py
linuxnet/qos/qdiscs/__init__.py
linuxnet/qos/qdiscs/drr.py
linuxnet/qos/qdiscs/fifo.py
linuxnet/qos/qdiscs/fq_codel.py
linuxnet/qos/qdiscs/htb.py
linuxnet/qos/qdiscs/ingress.py
linuxnet/qos/qdiscs/multiqueue.py
linuxnet/qos/qdiscs/netem.py
linuxnet/qos/qdiscs/prio.py
linuxnet/qos/qdiscs/qdisc.py
linuxnet/qos/qdiscs/sfq.py
linuxnet_qos-3.4.0.dist-info/LICENSE
linuxnet_qos-3.4.0.dist-info/METADATA
linuxnet_qos-3.4.0.dist-info/WHEEL
linuxnet_qos-3.4.0.dist-info/top_level.txt
linuxnet_qos-3.4.0.dist-info/RECORD
