Metadata-Version: 2.2
Name: linuxnet-qos
Version: 3.4.0
Summary: programmatic access to the Linux queuing disciplines
Home-page: https://gitlab.com/panos-tools/linuxnet-qos
Author: Panagiotis (Panos) Tsirigotis
Author-email: ptsirigotis01@gmail.com
License: AGPLv3
Project-URL: Source, https://gitlab.com/panos-tools/linuxnet-qos
Project-URL: Documentation, https://linuxnet-qos.readthedocs.io/en/latest/index.html
Classifier: Development Status :: 5 - Production/Stable
Classifier: Intended Audience :: Developers
Classifier: License :: OSI Approved :: GNU Affero General Public License v3
Classifier: Operating System :: POSIX :: Linux
Classifier: Programming Language :: Python :: 3 :: Only
Classifier: Topic :: Software Development :: Libraries
Classifier: Topic :: System :: Networking
Requires-Python: >=3.6
License-File: LICENSE
Dynamic: author
Dynamic: author-email
Dynamic: classifier
Dynamic: description
Dynamic: description-content-type
Dynamic: home-page
Dynamic: license
Dynamic: project-url
Dynamic: requires-python
Dynamic: summary
